curate_x_posts/__init__.py
curate_x_posts/__main__.py
curate_x_posts-0.0.7.dist-info/licenses/LICENSE
curate_x_posts-0.0.7.dist-info/METADATA
curate_x_posts-0.0.7.dist-info/WHEEL
curate_x_posts-0.0.7.dist-info/entry_points.txt
curate_x_posts-0.0.7.dist-info/top_level.txt
curate_x_posts-0.0.7.dist-info/RECORD
