Metadata-Version: 2.4
Name: curate-x-posts
Version: 0.0.7
Summary: A small package that curates posts from X social platform
Author-email: TCW <1470pancake@gmail.com>
License-Expression: MIT
Project-URL: Homepage, https://github.com/tcw1470/curate-x-posts
Project-URL: Issues, https://github.com/tcw1470/curate-x-posts/issues
Classifier: Programming Language :: Python :: 3
Classifier: Operating System :: OS Independent
Requires-Python: >=3.10
License-File: LICENSE
Requires-Dist: dotenv>=0.9.9
Requires-Dist: pandas>=2.2.3
Requires-Dist: twikit>=2.3.3
Dynamic: license-file
